{
  "version": "0.4.1",
  "flags": {},
  "shapes": [
    {
      "label": "pedestrian",
      "text": "pedestrian",
      "points": [
        [
          115,
          300
        ],
        [
          205,
          436
        ]
      ],
      "group_id": null,
      "shape_type": "rectangle",
      "flags": {
        "category": "pedestrian"
      }
    },
    {
      "label": "truck",
      "text": "truck",
      "points": [
        [
          609,
          258
        ],
        [
          677,
          337
        ]
      ],
      "group_id": null,
      "shape_type": "rectangle",
      "flags": {
        "category": "vehicle"
      }
    },
    {
      "label": "car",
      "text": "car",
      "points": [
        [
          732,
          279
        ],
        [
          868,
          355
        ]
      ],
      "group_id": null,
      "shape_type": "rectangle",
      "flags": {
        "category": "vehicle"
      }
    },
    {
      "label": "bus",
      "text": "bus",
      "points": [
        [
          728,
          256
        ],
        [
          786,
          309
        ]
      ],
      "group_id": null,
      "shape_type": "rectangle",
      "flags": {
        "category": "vehicle"
      }
    },
    {
      "label": "traffic_sign",
      "text": "traffic_sign",
      "points": [
        [
          430,
          423
        ],
        [
          723,
          489
        ]
      ],
      "group_id": null,
      "shape_type": "rectangle",
      "flags": {
        "category": "traffic_sign"
      }
    }
  ],
  "imagePath": "D4_000144.jpg",
  "imageData": null,
  "imageHeight": 720,
  "imageWidth": 1280
}