{
  "version": "0.4.1",
  "flags": {},
  "shapes": [
    {
      "label": "taxi",
      "text": "taxi",
      "points": [
        [
          210,
          387
        ],
        [
          384,
          494
        ]
      ],
      "group_id": null,
      "shape_type": "rectangle",
      "flags": {
        "category": "vehicle"
      }
    },
    {
      "label": "car",
      "text": "car",
      "points": [
        [
          509,
          346
        ],
        [
          567,
          387
        ]
      ],
      "group_id": null,
      "shape_type": "rectangle",
      "flags": {
        "category": "vehicle"
      }
    },
    {
      "label": "car",
      "text": "car",
      "points": [
        [
          602,
          336
        ],
        [
          644,
          361
        ]
      ],
      "group_id": null,
      "shape_type": "rectangle",
      "flags": {
        "category": "vehicle"
      }
    },
    {
      "label": "traffic_sign",
      "text": "traffic_sign",
      "points": [
        [
          704,
          251
        ],
        [
          737,
          275
        ]
      ],
      "group_id": null,
      "shape_type": "rectangle",
      "flags": {
        "category": "traffic_sign"
      }
    },
    {
      "label": "construction_barrier",
      "text": "construction_barrier",
      "points": [
        [
          719,
          310
        ],
        [
          865,
          375
        ]
      ],
      "group_id": null,
      "shape_type": "rectangle",
      "flags": {
        "category": "construction"
      }
    }
  ],
  "imagePath": "D4_001065.jpg",
  "imageData": null,
  "imageHeight": 720,
  "imageWidth": 1280
}