{
  "version": "0.4.1",
  "flags": {},
  "shapes": [
    {
      "label": "bus",
      "text": "bus",
      "points": [
        [
          0,
          0
        ],
        [
          593,
          567
        ]
      ],
      "group_id": null,
      "shape_type": "rectangle",
      "flags": {
        "category": "vehicle"
      }
    },
    {
      "label": "car_braking",
      "text": "car_braking",
      "points": [
        [
          701,
          306
        ],
        [
          869,
          406
        ]
      ],
      "group_id": null,
      "shape_type": "rectangle",
      "flags": {
        "category": "vehicle"
      }
    },
    {
      "label": "truck",
      "text": "truck",
      "points": [
        [
          677,
          284
        ],
        [
          745,
          356
        ]
      ],
      "group_id": null,
      "shape_type": "rectangle",
      "flags": {
        "category": "vehicle"
      }
    }
  ],
  "imagePath": "D4_000993.jpg",
  "imageData": null,
  "imageHeight": 720,
  "imageWidth": 1280
}