{
  "version": "0.4.1",
  "flags": {},
  "shapes": [
    {
      "label": "traffic_sign",
      "text": "traffic_sign",
      "points": [
        [
          134,
          29
        ],
        [
          662,
          155
        ]
      ],
      "group_id": null,
      "shape_type": "rectangle",
      "flags": {
        "category": "traffic_sign"
      }
    },
    {
      "label": "traffic_sign",
      "text": "traffic_sign",
      "points": [
        [
          147,
          122
        ],
        [
          662,
          198
        ]
      ],
      "group_id": null,
      "shape_type": "rectangle",
      "flags": {
        "category": "traffic_sign"
      }
    },
    {
      "label": "traffic_sign",
      "text": "traffic_sign",
      "points": [
        [
          1069,
          446
        ],
        [
          1277,
          598
        ]
      ],
      "group_id": null,
      "shape_type": "rectangle",
      "flags": {
        "category": "traffic_sign"
      }
    }
  ],
  "imagePath": "D4_001362.jpg",
  "imageData": null,
  "imageHeight": 720,
  "imageWidth": 1280
}