{
  "version": "0.4.1",
  "flags": {},
  "shapes": [
    {
      "label": "car",
      "text": "car",
      "points": [
        [
          0,
          333
        ],
        [
          453,
          525
        ]
      ],
      "group_id": null,
      "shape_type": "rectangle",
      "flags": {
        "category": "vehicle"
      }
    },
    {
      "label": "van",
      "text": "van",
      "points": [
        [
          680,
          310
        ],
        [
          758,
          389
        ]
      ],
      "group_id": null,
      "shape_type": "rectangle",
      "flags": {
        "category": "vehicle"
      }
    },
    {
      "label": "car",
      "text": "car",
      "points": [
        [
          549,
          340
        ],
        [
          625,
          384
        ]
      ],
      "group_id": null,
      "shape_type": "rectangle",
      "flags": {
        "category": "vehicle"
      }
    },
    {
      "label": "car",
      "text": "car",
      "points": [
        [
          648,
          337
        ],
        [
          676,
          361
        ]
      ],
      "group_id": null,
      "shape_type": "rectangle",
      "flags": {
        "category": "vehicle"
      }
    },
    {
      "label": "traffic_sign",
      "text": "traffic_sign",
      "points": [
        [
          749,
          307
        ],
        [
          796,
          324
        ]
      ],
      "group_id": null,
      "shape_type": "rectangle",
      "flags": {
        "category": "traffic_sign"
      }
    }
  ],
  "imagePath": "D4_000871.jpg",
  "imageData": null,
  "imageHeight": 720,
  "imageWidth": 1280
}