{
  "version": "0.4.1",
  "flags": {},
  "shapes": [
    {
      "label": "truck",
      "text": "truck",
      "points": [
        [
          0,
          140
        ],
        [
          305,
          395
        ]
      ],
      "group_id": null,
      "shape_type": "rectangle",
      "flags": {
        "category": "vehicle"
      }
    },
    {
      "label": "bus",
      "text": "bus",
      "points": [
        [
          539,
          270
        ],
        [
          591,
          328
        ]
      ],
      "group_id": null,
      "shape_type": "rectangle",
      "flags": {
        "category": "vehicle"
      }
    },
    {
      "label": "bus",
      "text": "bus",
      "points": [
        [
          644,
          260
        ],
        [
          763,
          376
        ]
      ],
      "group_id": null,
      "shape_type": "rectangle",
      "flags": {
        "category": "vehicle"
      }
    },
    {
      "label": "car",
      "text": "car",
      "points": [
        [
          337,
          296
        ],
        [
          442,
          350
        ]
      ],
      "group_id": null,
      "shape_type": "rectangle",
      "flags": {
        "category": "vehicle"
      }
    },
    {
      "label": "car",
      "text": "car",
      "points": [
        [
          444,
          294
        ],
        [
          495,
          337
        ]
      ],
      "group_id": null,
      "shape_type": "rectangle",
      "flags": {
        "category": "vehicle"
      }
    },
    {
      "label": "pedestrian",
      "text": "pedestrian",
      "points": [
        [
          310,
          284
        ],
        [
          329,
          328
        ]
      ],
      "group_id": null,
      "shape_type": "rectangle",
      "flags": {
        "category": "pedestrian"
      }
    }
  ],
  "imagePath": "D4_001153.jpg",
  "imageData": null,
  "imageHeight": 720,
  "imageWidth": 1280
}