{
  "version": "0.4.1",
  "flags": {},
  "shapes": [
    {
      "label": "traffic_sign",
      "text": "traffic_sign",
      "points": [
        [
          0,
          205
        ],
        [
          109,
          389
        ]
      ],
      "group_id": null,
      "shape_type": "rectangle",
      "flags": {
        "category": "traffic_sign"
      }
    },
    {
      "label": "motorcycle",
      "text": "motorcycle",
      "points": [
        [
          0,
          317
        ],
        [
          493,
          719
        ]
      ],
      "group_id": null,
      "shape_type": "rectangle",
      "flags": {
        "category": "vehicle"
      }
    },
    {
      "label": "motorcycle",
      "text": "motorcycle",
      "points": [
        [
          442,
          151
        ],
        [
          1279,
          719
        ]
      ],
      "group_id": null,
      "shape_type": "rectangle",
      "flags": {
        "category": "vehicle"
      }
    },
    {
      "label": "pedestrian",
      "text": "pedestrian",
      "points": [
        [
          672,
          243
        ],
        [
          691,
          277
        ]
      ],
      "group_id": null,
      "shape_type": "rectangle",
      "flags": {
        "category": "pedestrian"
      }
    }
  ],
  "imagePath": "D4_001486.jpg",
  "imageData": null,
  "imageHeight": 720,
  "imageWidth": 1280
}