{
  "version": "0.4.1",
  "flags": {},
  "shapes": [
    {
      "label": "pedestrian",
      "text": "pedestrian",
      "points": [
        [
          602,
          264
        ],
        [
          617,
          292
        ]
      ],
      "group_id": null,
      "shape_type": "rectangle",
      "flags": {
        "category": "pedestrian"
      }
    },
    {
      "label": "car",
      "text": "car",
      "points": [
        [
          31,
          303
        ],
        [
          302,
          402
        ]
      ],
      "group_id": null,
      "shape_type": "rectangle",
      "flags": {
        "category": "vehicle"
      }
    }
  ],
  "imagePath": "D4_000062.jpg",
  "imageData": null,
  "imageHeight": 720,
  "imageWidth": 1280
}