{
  "version": "0.4.1",
  "flags": {},
  "shapes": [
    {
      "label": "car",
      "text": "car",
      "points": [
        [
          652,
          304
        ],
        [
          790,
          412
        ]
      ],
      "group_id": null,
      "shape_type": "rectangle",
      "flags": {
        "category": "vehicle"
      }
    },
    {
      "label": "car",
      "text": "car",
      "points": [
        [
          883,
          296
        ],
        [
          1229,
          444
        ]
      ],
      "group_id": null,
      "shape_type": "rectangle",
      "flags": {
        "category": "vehicle"
      }
    },
    {
      "label": "car",
      "text": "car",
      "points": [
        [
          579,
          317
        ],
        [
          643,
          364
        ]
      ],
      "group_id": null,
      "shape_type": "rectangle",
      "flags": {
        "category": "vehicle"
      }
    },
    {
      "label": "car",
      "text": "car",
      "points": [
        [
          792,
          323
        ],
        [
          856,
          365
        ]
      ],
      "group_id": null,
      "shape_type": "rectangle",
      "flags": {
        "category": "vehicle"
      }
    }
  ],
  "imagePath": "D4_000679.jpg",
  "imageData": null,
  "imageHeight": 720,
  "imageWidth": 1280
}