{
  "version": "0.4.1",
  "flags": {},
  "shapes": [
    {
      "label": "bus",
      "text": "bus",
      "points": [
        [
          0,
          0
        ],
        [
          438,
          565
        ]
      ],
      "group_id": null,
      "shape_type": "rectangle",
      "flags": {
        "category": "vehicle"
      }
    },
    {
      "label": "bus_braking",
      "text": "bus_braking",
      "points": [
        [
          378,
          213
        ],
        [
          677,
          448
        ]
      ],
      "group_id": null,
      "shape_type": "rectangle",
      "flags": {
        "category": "vehicle"
      }
    },
    {
      "label": "van",
      "text": "van",
      "points": [
        [
          691,
          40
        ],
        [
          1271,
          544
        ]
      ],
      "group_id": null,
      "shape_type": "rectangle",
      "flags": {
        "category": "vehicle"
      }
    },
    {
      "label": "traffic_sign",
      "text": "traffic_sign",
      "points": [
        [
          1167,
          73
        ],
        [
          1235,
          140
        ]
      ],
      "group_id": null,
      "shape_type": "rectangle",
      "flags": {
        "category": "traffic_sign"
      }
    }
  ],
  "imagePath": "D4_001219.jpg",
  "imageData": null,
  "imageHeight": 720,
  "imageWidth": 1280
}